Metadata-Version: 1.0
Name: magichome
Version: 0.1.79
Summary: Magic Home Smart API
Home-page: https://github.com/ZNEGGE-SDK/magichome
Author: zengge
Author-email: cnzengge@gmail.com
License: MIT
Keywords: pip,magichome,Zengge smart Home
Platform: any
